pypylon/libNodeMapData_gcc_v3_1_Basler_pylon_v3.so
pypylon/libLog_gcc_v3_1_Basler_pylon_v3.so
pypylon/libgxapi.so.15
pypylon/libpylon_TL_camemu.so
pypylon/libPylonDataProcessingCore.so.4
pypylon/liblog4cpp_gcc_v3_1_Basler_pylon_v3.so
pypylon/libPylonDataProcessing.sig
pypylon/libGCBase_gcc_v3_1_Basler_pylon_v3.so
pypylon/__init__.py
pypylon/_genicam.abi3.so
pypylon/genicam.py
pypylon/libPylonDataProcessing.so.3
pypylon/libpylonbase.so.10
pypylon/_pylon.abi3.so
pypylon/libXmlParser_gcc_v3_1_Basler_pylon_v3.so
pypylon/libpylon_TL_gtc.so
pypylon/libGenApi_gcc_v3_1_Basler_pylon_v3.so
pypylon/libpylonutility.so.10
pypylon/libMathParser_gcc_v3_1_Basler_pylon_v3.so
pypylon/libpylon_TL_gige.so
pypylon/pylondataprocessing.py
pypylon/libpylon_TL_usb.so
pypylon/pylon.py
pypylon/libuxapi.so.14
pypylon/_pylondataprocessing.abi3.so
pypylon/pylon-libusb-1.0.27.so
pypylon/pylondataprocessingplugins/libPylonVToolAdapter.so
pypylon/pylondataprocessingplugins/libPylonVToolPackageA_asl.lic
pypylon/pylondataprocessingplugins/libPylonVToolPackageA.so
pypylon/pylondataprocessingplugins/libPylonVToolPackageBase.so
pypylon/pylondataprocessingplugins/libPylonAIvToolPackage.so
pypylon/pylondataprocessingplugins/libPylonVToolPackageB.so
pypylon/pylondataprocessingplugins/PylonVToolPackageA/CalibrationPlate_60mm.pcal
pypylon/pylondataprocessingplugins/PylonVToolPackageA/CalibrationPlate_400mm.pcal
pypylon/pylondataprocessingplugins/PylonVToolPackageA/CalibrationPlate_1600mm.pdf
pypylon/pylondataprocessingplugins/PylonVToolPackageA/CalibrationPlate_800mm.pcal
pypylon/pylondataprocessingplugins/PylonVToolPackageA/CalibrationPlate_1200mm.pdf
pypylon/pylondataprocessingplugins/PylonVToolPackageA/CalibrationPlate_120mm.pdf
pypylon/pylondataprocessingplugins/PylonVToolPackageA/CalibrationPlate_240mm.pdf
pypylon/pylondataprocessingplugins/PylonVToolPackageA/CalibrationPlate_1200mm.pcal
pypylon-4.2.0.dist-info/WHEEL
pypylon-4.2.0.dist-info/METADATA
pypylon-4.2.0.dist-info/LICENSE
pypylon-4.2.0.dist-info/RECORD
pypylon-4.2.0.dist-info/top_level.txt
