Metadata-Version: 2.1
Name: pypylon
Version: 4.2.0
Summary: The python wrapper for the Basler pylon Camera Software Suite.
Home-page: https://github.com/basler/pypylon
Author: Basler AG
Author-email: oss@baslerweb.com
License: Other/Proprietary License
Classifier: License :: Other/Proprietary License
Classifier: Programming Language :: C++
Classifier: Operating System :: Microsoft :: Windows :: Windows 7
Classifier: Operating System :: Microsoft :: Windows :: Windows 8
Classifier: Operating System :: Microsoft :: Windows :: Windows 10
Classifier: Operating System :: Microsoft :: Windows :: Windows 11
Classifier: Operating System :: POSIX :: Linux
Classifier: Operating System :: MacOS :: MacOS X
Classifier: Topic :: Multimedia :: Graphics :: Capture :: Digital Camera
Classifier: Topic :: Multimedia :: Video :: Capture
Classifier: Topic :: Scientific/Engineering
License-File: LICENSE
